unconference/__init__.py
unconference/_version.py
unconference/admin.py
unconference/apps.py
unconference/decorators.py
unconference/models.py
unconference/settings.py
unconference/urls.py
unconference/views.py
unconference/migrations/0001_initial.py
unconference/migrations/0002_usereventdata.py
unconference/migrations/0003_location_remove_room_unique_room_and_more.py
unconference/migrations/__init__.py
unconference/templates/unconference/home.html
unconference/templates/unconference/schedule.html
unconference-1.0.0.dev9.dist-info/METADATA
unconference-1.0.0.dev9.dist-info/WHEEL
unconference-1.0.0.dev9.dist-info/top_level.txt
unconference-1.0.0.dev9.dist-info/RECORD
